setup.py
cpsvisualizer/__init__.py
cpsvisualizer/__main__.py
cpsvisualizer/app.py
cpsvisualizer/app_cli.py
cpsvisualizer/requirements.txt
cpsvisualizer/test.py
cpsvisualizer.egg-info/PKG-INFO
cpsvisualizer.egg-info/SOURCES.txt
cpsvisualizer.egg-info/dependency_links.txt
cpsvisualizer.egg-info/requires.txt
cpsvisualizer.egg-info/top_level.txt